[
    {
        "release_date": "2026-03-06",
        "title": "暗黑新娘！",
        "genre": "['剧情', '犯罪', '惊悚']",
        "region": "['美国']",
        "want_to_see": 12663,
        "url": "https://movie.douban.com/subject/36503073/",
        "old_release_date": "2026-03-06",
        "status": "Upcoming"
    },
    {
        "release_date": "2026-03-07",
        "title": "洛杉矶劫案",
        "genre": "['剧情', '动作', '犯罪']",
        "region": "['美国', '英国']",
        "want_to_see": 5567,
        "url": "https://movie.douban.com/subject/36901008/",
        "old_release_date": "2026-03-07",
        "status": "Upcoming"
    },
    {
        "release_date": "2026-03-08",
        "title": "非穷尽列举",
        "genre": "['剧情']",
        "region": "['英国']",
        "want_to_see": 24373,
        "url": "https://movie.douban.com/subject/37293378/",
        "old_release_date": "2026-03-08",
        "status": "Upcoming"
    },
    {
        "release_date": "2026-03-13",
        "title": "呼啸山庄",
        "genre": "['剧情', '爱情']",
        "region": "['英国', '美国']",
        "want_to_see": 23910,
        "url": "https://movie.douban.com/subject/36963690/",
        "old_release_date": "2026-03-13",
        "status": "Upcoming"
    },
    {
        "release_date": "2026-03-14",
        "title": "奇迹梦之队",
        "genre": "['喜剧', '动画', '冒险']",
        "region": "['美国']",
        "want_to_see": 2390,
        "url": "https://movie.douban.com/subject/36910970/",
        "old_release_date": "2026-03-14",
        "status": "Upcoming"
    },
    {
        "release_date": "2026-03-14",
        "title": "拼桌",
        "genre": "['喜剧', '爱情']",
        "region": "['中国大陆']",
        "want_to_see": 2024,
        "url": "https://movie.douban.com/subject/36539452/",
        "old_release_date": "2026-03-14",
        "status": "Upcoming"
    },
    {
        "release_date": "2026-03-14",
        "title": "上学路上之山海无阻",
        "genre": "['纪录片']",
        "region": "['中国大陆']",
        "want_to_see": 381,
        "url": "https://movie.douban.com/subject/36650727/",
        "old_release_date": "2026-03-14",
        "status": "Upcoming"
    },
    {
        "release_date": "2026-03-20",
        "title": "至尊马蒂",
        "genre": "['剧情', '运动']",
        "region": "['芬兰', '美国']",
        "want_to_see": 20228,
        "url": "https://movie.douban.com/subject/36691620/",
        "old_release_date": "2026-03-20",
        "status": "Upcoming"
    },
    {
        "release_date": "2026-03-20",
        "title": "挽救计划",
        "genre": "['动作', '科幻', '冒险']",
        "region": "['美国']",
        "want_to_see": 18431,
        "url": "https://movie.douban.com/subject/35010610/",
        "old_release_date": "2026-03-20",
        "status": "Upcoming"
    },
    {
        "release_date": "2026-03-20",
        "title": "河狸变身计划",
        "genre": "['喜剧', '科幻', '动画']",
        "region": "['美国']",
        "want_to_see": 7344,
        "url": "https://movie.douban.com/subject/36999793/",
        "old_release_date": "2026-03-20",
        "status": "Upcoming"
    },
    {
        "release_date": "2026-03-20",
        "title": "时间旅馆",
        "genre": "['剧情', '爱情']",
        "region": "['中国大陆']",
        "want_to_see": 1005,
        "url": "https://movie.douban.com/subject/35700764/",
        "old_release_date": "2026-03-20",
        "status": "Upcoming"
    },
    {
        "release_date": "2026-03-??",
        "title": "穿普拉达的女王",
        "genre": "['剧情', '喜剧']",
        "region": "['美国', '法国']",
        "want_to_see": 118680,
        "url": "https://movie.douban.com/subject/1482072/",
        "old_release_date": "2026-03-99",
        "status": "Upcoming"
    },
    {
        "release_date": "2026-03-??",
        "title": "搜查瑠公圳",
        "genre": "['剧情', '历史', '犯罪']",
        "region": "['中国台湾']",
        "want_to_see": 686,
        "url": "https://movie.douban.com/subject/35736046/",
        "old_release_date": "2026-03-99",
        "status": "Upcoming"
    },
    {
        "release_date": "2026-04-03",
        "title": "北回归线以北",
        "genre": "['剧情']",
        "region": "['中国大陆']",
        "want_to_see": 601,
        "url": "https://movie.douban.com/subject/36941236/",
        "old_release_date": "2026-04-03",
        "status": "Upcoming"
    },
    {
        "release_date": "2026-04-03",
        "title": "凌晨两点半3",
        "genre": "['惊悚', '恐怖']",
        "region": "['中国大陆']",
        "want_to_see": 200,
        "url": "https://movie.douban.com/subject/36990246/",
        "old_release_date": "2026-04-03",
        "status": "Upcoming"
    },
    {
        "release_date": "2026-04-04",
        "title": "天才游戏",
        "genre": "['犯罪', '悬疑']",
        "region": "['中国大陆']",
        "want_to_see": 14139,
        "url": "https://movie.douban.com/subject/35159709/",
        "old_release_date": "2026-04-04",
        "status": "Upcoming"
    },
    {
        "release_date": "2026-05-01",
        "title": "千金不换",
        "genre": "['剧情', '喜剧']",
        "region": "['中国大陆']",
        "want_to_see": 3237,
        "url": "https://movie.douban.com/subject/36918875/",
        "old_release_date": "2026-05-01",
        "status": "Upcoming"
    },
    {
        "release_date": "2026-05-20",
        "title": "为我的心动买单",
        "genre": "['喜剧', '爱情']",
        "region": "['中国大陆']",
        "want_to_see": 1824,
        "url": "https://movie.douban.com/subject/37350266/",
        "old_release_date": "2026-05-20",
        "status": "Upcoming"
    },
    {
        "release_date": "2026-05-20",
        "title": "错过了，遗憾吗？",
        "genre": "['喜剧', '爱情']",
        "region": "['中国大陆']",
        "want_to_see": 1703,
        "url": "https://movie.douban.com/subject/36117834/",
        "old_release_date": "2026-05-20",
        "status": "Upcoming"
    },
    {
        "release_date": "2026-07-??",
        "title": "大唐妖探",
        "genre": "['喜剧', '动画', '悬疑']",
        "region": "['中国大陆']",
        "want_to_see": 632,
        "url": "https://movie.douban.com/subject/35464353/",
        "old_release_date": "2026-07-99",
        "status": "Upcoming"
    },
    {
        "release_date": "2027-02-06",
        "title": "流浪地球3(上)",
        "genre": "['科幻', '冒险', '灾难']",
        "region": "['中国大陆']",
        "want_to_see": 91554,
        "url": "https://movie.douban.com/subject/36212391/",
        "old_release_date": "2027-02-06",
        "status": "Upcoming"
    }
]