[
    {
        "release_date": "2026-04-30",
        "title": "给阿嬷的情书",
        "genre": "['剧情', '家庭']",
        "region": "['中国大陆']",
        "want_to_see": 6341,
        "url": "https://movie.douban.com/subject/37116446/",
        "old_release_date": "2026-04-30",
        "status": "Upcoming"
    },
    {
        "release_date": "2026-05-01",
        "title": "寒战1994",
        "genre": "['剧情', '动作', '犯罪']",
        "region": "['中国香港', '中国大陆']",
        "want_to_see": 15427,
        "url": "https://movie.douban.com/subject/36857924/",
        "old_release_date": "2026-05-01",
        "status": "Upcoming"
    },
    {
        "release_date": "2026-05-01",
        "title": "消失的人",
        "genre": "['犯罪', '悬疑', '惊悚']",
        "region": "['中国大陆']",
        "want_to_see": 4122,
        "url": "https://movie.douban.com/subject/36965301/",
        "old_release_date": "2026-05-01",
        "status": "Upcoming"
    },
    {
        "release_date": "2026-05-01",
        "title": "10间敢死队",
        "genre": "['剧情', '喜剧']",
        "region": "['中国大陆']",
        "want_to_see": 3229,
        "url": "https://movie.douban.com/subject/37379599/",
        "old_release_date": "2026-05-01",
        "status": "Upcoming"
    },
    {
        "release_date": "2026-05-01",
        "title": "三心两意",
        "genre": "['剧情', '喜剧', '爱情']",
        "region": "['中国大陆']",
        "want_to_see": 1727,
        "url": "https://movie.douban.com/subject/36613824/",
        "old_release_date": "2026-05-01",
        "status": "Upcoming"
    },
    {
        "release_date": "2026-05-01",
        "title": "门牙",
        "genre": "['剧情']",
        "region": "['中国大陆']",
        "want_to_see": 1429,
        "url": "https://movie.douban.com/subject/37534660/",
        "old_release_date": "2026-05-01",
        "status": "Upcoming"
    },
    {
        "release_date": "2026-05-01",
        "title": "猪猪侠大电影之竞速小英雄",
        "genre": "['喜剧', '动画', '奇幻']",
        "region": "['中国大陆']",
        "want_to_see": 239,
        "url": "https://movie.douban.com/subject/37193307/",
        "old_release_date": "2026-05-01",
        "status": "Upcoming"
    },
    {
        "release_date": "2026-05-03",
        "title": "纵横四海",
        "genre": "['剧情', '喜剧', '动作']",
        "region": "['中国香港']",
        "want_to_see": 196955,
        "url": "https://movie.douban.com/subject/1295409/",
        "old_release_date": "2026-05-03",
        "status": "Upcoming"
    },
    {
        "release_date": "2026-05-08",
        "title": "真人快打2",
        "genre": "['动作', '科幻', '奇幻']",
        "region": "['美国']",
        "want_to_see": 4940,
        "url": "https://movie.douban.com/subject/35754057/",
        "old_release_date": "2026-05-08",
        "status": "Upcoming"
    },
    {
        "release_date": "2026-05-08",
        "title": "青铜葵花",
        "genre": "['剧情']",
        "region": "['中国大陆']",
        "want_to_see": 2347,
        "url": "https://movie.douban.com/subject/36500314/",
        "old_release_date": "2026-05-08",
        "status": "Upcoming"
    },
    {
        "release_date": "2026-05-13",
        "title": "再见，朱莉娅",
        "genre": "['剧情']",
        "region": "['苏丹', '瑞典']",
        "want_to_see": 12601,
        "url": "https://movie.douban.com/subject/36070920/",
        "old_release_date": "2026-05-13",
        "status": "Upcoming"
    },
    {
        "release_date": "2026-05-15",
        "title": "大白鲨",
        "genre": "['剧情', '惊悚', '冒险']",
        "region": "['美国']",
        "want_to_see": 32249,
        "url": "https://movie.douban.com/subject/1294941/",
        "old_release_date": "2026-05-15",
        "status": "New"
    },
    {
        "release_date": "2026-05-16",
        "title": "绵羊侦探团",
        "genre": "['喜剧', '动作', '悬疑']",
        "region": "['爱尔兰', '英国']",
        "want_to_see": 8280,
        "url": "https://movie.douban.com/subject/36918069/",
        "old_release_date": "2026-05-16",
        "status": "Upcoming"
    },
    {
        "release_date": "2026-05-16",
        "title": "一个男人和一个女人",
        "genre": "['剧情']",
        "region": "['中国大陆', '中国香港']",
        "want_to_see": 6991,
        "url": "https://movie.douban.com/subject/36311696/",
        "old_release_date": "2026-05-16",
        "status": "Upcoming"
    },
    {
        "release_date": "2026-05-20",
        "title": "错过了，遗憾吗？",
        "genre": "['喜剧', '爱情']",
        "region": "['中国大陆']",
        "want_to_see": 2279,
        "url": "https://movie.douban.com/subject/36117834/",
        "old_release_date": "2026-05-20",
        "status": "Upcoming"
    },
    {
        "release_date": "2026-05-20",
        "title": "为我的心动买单",
        "genre": "['喜剧', '爱情']",
        "region": "['中国大陆']",
        "want_to_see": 2091,
        "url": "https://movie.douban.com/subject/37350266/",
        "old_release_date": "2026-05-20",
        "status": "Upcoming"
    },
    {
        "release_date": "2026-05-20",
        "title": "错时告白",
        "genre": "['剧情', '喜剧', '爱情']",
        "region": "['泰国']",
        "want_to_see": 1655,
        "url": "https://movie.douban.com/subject/35903155/",
        "old_release_date": "2026-05-20",
        "status": "Upcoming"
    },
    {
        "release_date": "2026-05-22",
        "title": "星球大战：曼达洛人与古古",
        "genre": "['动作', '科幻', '奇幻']",
        "region": "['美国']",
        "want_to_see": 9787,
        "url": "https://movie.douban.com/subject/36723035/",
        "old_release_date": "2026-05-22",
        "status": "Upcoming"
    },
    {
        "release_date": "2026-05-22",
        "title": "今晚正好",
        "genre": "['剧情', '喜剧', '爱情']",
        "region": "['中国大陆']",
        "want_to_see": 2322,
        "url": "https://movie.douban.com/subject/37317133/",
        "old_release_date": "2026-05-22",
        "status": "Upcoming"
    },
    {
        "release_date": "2026-05-23",
        "title": "森中有林",
        "genre": "['剧情', '爱情', '犯罪']",
        "region": "['中国大陆']",
        "want_to_see": 7632,
        "url": "https://movie.douban.com/subject/36372941/",
        "old_release_date": "2026-05-23",
        "status": "Upcoming"
    },
    {
        "release_date": "2026-05-29",
        "title": "记忆碎片",
        "genre": "['犯罪', '剧情', '悬疑']",
        "region": "['美国']",
        "want_to_see": 390269,
        "url": "https://movie.douban.com/subject/1304447/",
        "old_release_date": "2026-05-29",
        "status": "New"
    },
    {
        "release_date": "2026-06-19",
        "title": "爱是愤怒",
        "genre": "['爱情', '犯罪']",
        "region": "['中国大陆']",
        "want_to_see": 2915,
        "url": "https://movie.douban.com/subject/37152802/",
        "old_release_date": "2026-06-19",
        "status": "Upcoming"
    },
    {
        "release_date": "2026-06-19",
        "title": "绝密任务",
        "genre": "['动作', '战争', '犯罪']",
        "region": "['中国大陆']",
        "want_to_see": 1624,
        "url": "https://movie.douban.com/subject/34833849/",
        "old_release_date": "2026-06-19",
        "status": "Upcoming"
    },
    {
        "release_date": "2026-06-26",
        "title": "四渡",
        "genre": "['历史', '战争']",
        "region": "['中国大陆']",
        "want_to_see": 3203,
        "url": "https://movie.douban.com/subject/37191746/",
        "old_release_date": "2026-06-26",
        "status": "Upcoming"
    },
    {
        "release_date": "2026-06-??",
        "title": "玩具总动员5",
        "genre": "['剧情', '喜剧', '动画']",
        "region": "['美国', '日本']",
        "want_to_see": 26378,
        "url": "https://movie.douban.com/subject/36238849/",
        "old_release_date": "2026-06-99",
        "status": "Upcoming"
    },
    {
        "release_date": "2026-06-??",
        "title": "森林之声",
        "genre": "['剧情', '动画']",
        "region": "['英国']",
        "want_to_see": 26,
        "url": "https://movie.douban.com/subject/35575521/",
        "old_release_date": "2026-06-99",
        "status": "New"
    },
    {
        "release_date": "2026-07-10",
        "title": "三国第一部：争洛阳",
        "genre": "['历史', '动画']",
        "region": "['中国大陆']",
        "want_to_see": 2028,
        "url": "https://movie.douban.com/subject/36752981/",
        "old_release_date": "2026-07-10",
        "status": "Upcoming"
    },
    {
        "release_date": "2026-07-10",
        "title": "大圣崛起",
        "genre": "['动画', '奇幻', '冒险']",
        "region": "['中国大陆']",
        "want_to_see": 1929,
        "url": "https://movie.douban.com/subject/26822087/",
        "old_release_date": "2026-07-10",
        "status": "Upcoming"
    },
    {
        "release_date": "2026-07-??",
        "title": "小黄人与大怪兽",
        "genre": "['喜剧', '科幻', '动画']",
        "region": "['美国']",
        "want_to_see": 4978,
        "url": "https://movie.douban.com/subject/36962219/",
        "old_release_date": "2026-07-99",
        "status": "Upcoming"
    },
    {
        "release_date": "2026-07-??",
        "title": "大唐妖探",
        "genre": "['喜剧', '动画', '悬疑']",
        "region": "['中国大陆']",
        "want_to_see": 1124,
        "url": "https://movie.douban.com/subject/35464353/",
        "old_release_date": "2026-07-99",
        "status": "Upcoming"
    },
    {
        "release_date": "2027-02-06",
        "title": "流浪地球3(上)",
        "genre": "['科幻', '冒险', '灾难']",
        "region": "['中国大陆']",
        "want_to_see": 94454,
        "url": "https://movie.douban.com/subject/36212391/",
        "old_release_date": "2027-02-06",
        "status": "Upcoming"
    },
    {
        "release_date": "2027-02-??",
        "title": "守密者",
        "genre": "['剧情']",
        "region": "['中国大陆']",
        "want_to_see": 281,
        "url": "https://movie.douban.com/subject/37497264/",
        "old_release_date": "2027-02-99",
        "status": "Upcoming"
    }
]